ownlayer_sdk/__init__.py
ownlayer_sdk/openai.py
ownlayer_sdk/ownlayer_api.py
ownlayer_sdk-0.1.0.dist-info/LICENSE
ownlayer_sdk-0.1.0.dist-info/METADATA
ownlayer_sdk-0.1.0.dist-info/WHEEL
ownlayer_sdk-0.1.0.dist-info/RECORD
